flask_auth_user/Manager.py
flask_auth_user/__init__.py
flask_auth_user/helper/mini/MiniHelper.py
flask_auth_user/helper/mini/__init__.py
flask_auth_user/helper/sms/SmsHelper.py
flask_auth_user/helper/sms/__init__.py
flask_auth_user/helper/token/.DS_Store
flask_auth_user/helper/token/TokenHelper.py
flask_auth_user/helper/token/__init__.py
flask_auth_user/utils/token/Token.py
flask_auth_user/utils/token/__init__.py
Flask_Auth_User-1.0.2.dist-info/METADATA
Flask_Auth_User-1.0.2.dist-info/WHEEL
Flask_Auth_User-1.0.2.dist-info/top_level.txt
Flask_Auth_User-1.0.2.dist-info/RECORD
